{"cameraMode":{"drawMode":0,"name":"Shaded","section":"Shading Mode"},"sceneLighting":false,"audioPlay":false,"sceneViewState":{"m_AlwaysRefresh":false,"showFog":true,"showSkybox":false,"showFlares":true,"showImageEffects":true,"showParticleSystems":true,"showVisualEffectGraphs":true,"m_FxEnabled":true},"in2DMode":false,"pivot":{"x":-11.725826263427735,"y":3.290050983428955,"z":9.76562786102295},"rotation":{"x":0.1487024426460266,"y":-0.7553839087486267,"z":0.18661265075206757,"w":0.6111947298049927},"size":4.650032997131348,"orthographic":false}